seaborn/__init__.py
seaborn/_base.py
seaborn/_compat.py
seaborn/_docstrings.py
seaborn/_statistics.py
seaborn/_testing.py
seaborn/algorithms.py
seaborn/axisgrid.py
seaborn/categorical.py
seaborn/cm.py
seaborn/distributions.py
seaborn/matrix.py
seaborn/miscplot.py
seaborn/objects.py
seaborn/palettes.py
seaborn/rcmod.py
seaborn/regression.py
seaborn/relational.py
seaborn/utils.py
seaborn/widgets.py
seaborn/_core/__init__.py
seaborn/_core/data.py
seaborn/_core/exceptions.py
seaborn/_core/groupby.py
seaborn/_core/moves.py
seaborn/_core/plot.py
seaborn/_core/properties.py
seaborn/_core/rules.py
seaborn/_core/scales.py
seaborn/_core/subplots.py
seaborn/_core/typing.py
seaborn/_marks/__init__.py
seaborn/_marks/area.py
seaborn/_marks/bar.py
seaborn/_marks/base.py
seaborn/_marks/dot.py
seaborn/_marks/line.py
seaborn/_marks/text.py
seaborn/_stats/__init__.py
seaborn/_stats/aggregation.py
seaborn/_stats/base.py
seaborn/_stats/counting.py
seaborn/_stats/density.py
seaborn/_stats/order.py
seaborn/_stats/regression.py
seaborn/colors/__init__.py
seaborn/colors/crayons.py
seaborn/colors/xkcd_rgb.py
seaborn/external/__init__.py
seaborn/external/appdirs.py
seaborn/external/docscrape.py
seaborn/external/husl.py
seaborn/external/kde.py
seaborn/external/version.py
seaborn_qpython-0.13.2.dist-info/METADATA
seaborn_qpython-0.13.2.dist-info/WHEEL
seaborn_qpython-0.13.2.dist-info/top_level.txt
seaborn_qpython-0.13.2.dist-info/RECORD
