Metadata-Version: 2.4
Name: seaborn-qpython
Version: 0.13.2
Summary: seaborn: statistical data visualization
Author-email: The QPYPI Team <qpypi@qpython.org>
License: MIT AND (Apache-2.0 OR BSD-2-Clause)
Project-URL: Homepage, https://qpypi.qpython.org/project/seaborn-qpython/
Classifier: Intended Audience :: Developers
Classifier: Intended Audience :: Education
Classifier: Intended Audience :: Information Technology
Classifier: Intended Audience :: End Users/Desktop
Classifier: License :: OSI Approved :: Apache Software License
Classifier: Operating System :: Android
Classifier: Programming Language :: Python
Classifier: Programming Language :: Python :: 3.12
Classifier: Topic :: Software Development
Requires-Python: ==3.12.*
Requires-Dist: matplotlib-aipy
Requires-Dist: pandas-aipy
Requires-Dist: numpy-aipy
